[
  {
    "ContainingType": "spacexinterop.api.Controllers.AuthController",
    "Method": "CheckSession",
    "RelativePath": "api/Auth/CheckSession",
    "HttpMethod": "GET",
    "IsController": true,
    "Order": 0,
    "Parameters": [],
    "ReturnTypes": []
  },
  {
    "ContainingType": "spacexinterop.api.Controllers.AuthController",
    "Method": "Login",
    "RelativePath": "api/Auth/Login",
    "HttpMethod": "POST",
    "IsController": true,
    "Order": 0,
    "Parameters": [
      {
        "Name": "request",
        "Type": "spacexinterop.api.Data.Request.LoginRequest",
        "IsRequired": true
      }
    ],
    "ReturnTypes": []
  },
  {
    "ContainingType": "spacexinterop.api.Controllers.AuthController",
    "Method": "Logout",
    "RelativePath": "api/Auth/Logout",
    "HttpMethod": "POST",
    "IsController": true,
    "Order": 0,
    "Parameters": [],
    "ReturnTypes": []
  },
  {
    "ContainingType": "spacexinterop.api.Controllers.AuthController",
    "Method": "Register",
    "RelativePath": "api/Auth/Register",
    "HttpMethod": "POST",
    "IsController": true,
    "Order": 0,
    "Parameters": [
      {
        "Name": "request",
        "Type": "spacexinterop.api.Data.Request.RegisterRequest",
        "IsRequired": true
      }
    ],
    "ReturnTypes": []
  },
  {
    "ContainingType": "spacexinterop.api.Controllers.SpaceXController",
    "Method": "GetLaunches",
    "RelativePath": "api/SpaceX/GetLaunches",
    "HttpMethod": "POST",
    "IsController": true,
    "Order": 0,
    "Parameters": [
      {
        "Name": "request",
        "Type": "spacexinterop.api.Data.Request.SpaceXLaunchesRequest",
        "IsRequired": true
      }
    ],
    "ReturnTypes": []
  }
]